birdfeeder/__init__.py
birdfeeder/async_diagnosis.py
birdfeeder/async_utils.py
birdfeeder/aws/__init__.py
birdfeeder/aws/autoscaling.py
birdfeeder/aws/base.py
birdfeeder/aws/exceptions.py
birdfeeder/aws/s3.py
birdfeeder/build_image.py
birdfeeder/datetime_constants.py
birdfeeder/datetime_helpers.py
birdfeeder/enum/__init__.py
birdfeeder/enum/str_enum.py
birdfeeder/json_helpers.py
birdfeeder/kafka.py
birdfeeder/liveness_api.py
birdfeeder/logging.py
birdfeeder/management_console.py
birdfeeder/math_helpers.py
birdfeeder/pydantic/__init__.py
birdfeeder/pydantic/base_settings.py
birdfeeder/pytest_fixtures.py
birdfeeder/sample_configs/redis_sentinel_config
birdfeeder/sqlalchemy/__init__.py
birdfeeder/sqlalchemy/explain_helper.py
birdfeeder/subprocess.py
birdfeeder/timed_aggregator.py
birdfeeder/timestamps.py
birdfeeder/typing_local.py
birdfeeder_coinalpha-1.4.1.dist-info/LICENSE.md
birdfeeder_coinalpha-1.4.1.dist-info/METADATA
birdfeeder_coinalpha-1.4.1.dist-info/WHEEL
birdfeeder_coinalpha-1.4.1.dist-info/entry_points.txt
birdfeeder_coinalpha-1.4.1.dist-info/RECORD
