Metadata-Version: 2.1
Name: birdfeeder-coinalpha
Version: 1.4.1
Summary: Helper library for CoinAlpha projects
Home-page: https://github.com/coinalpha/birdfeeder
License: MIT
Author: Vladimir Kamarzin
Author-email: vvk@vvk.pp.ru
Requires-Python: >=3.8,<4.0
Classifier: Development Status :: 5 - Production/Stable
Classifier: Intended Audience :: Developers
Classifier: License :: OSI Approved :: MIT License
Classifier: Operating System :: OS Independent
Classifier: Programming Language :: Python :: 3
Classifier: Programming Language :: Python :: 3.8
Classifier: Programming Language :: Python :: 3.9
Classifier: Programming Language :: Python :: 3.10
Classifier: Programming Language :: Python :: 3.11
Classifier: Programming Language :: Python :: 3.12
Classifier: Programming Language :: Python :: 3.13
Classifier: Topic :: Software Development :: Libraries :: Python Modules
Requires-Dist: aioconsole (>=0.1.16)
Requires-Dist: aiohttp (>=3.2,<4.0)
Requires-Dist: aiorun (>=2020,<2021)
Requires-Dist: async-timeout
Requires-Dist: boto3 (>=1,<2)
Requires-Dist: cachetools (>=4,<5)
Requires-Dist: environs (>=9,<10)
Requires-Dist: kafka-python (>=2,<3)
Requires-Dist: pandas (>=1.1,<2.0)
Requires-Dist: pydantic (>=1.9.0,<2.0.0)
Requires-Dist: python-json-logger (>=2,<3)
Requires-Dist: ruamel.yaml (>=0.16,<0.17)
Requires-Dist: typer (>=0.3)
Project-URL: Repository, https://github.com/coinalpha/birdfeeder
